opentelemetry/py.typed
opentelemetry/propagators/cloud_trace_propagator/__init__.py
opentelemetry/propagators/cloud_trace_propagator/version.py
opentelemetry_propagator_gcp-1.11.0.dist-info/licenses/LICENSE
opentelemetry_propagator_gcp-1.11.0.dist-info/METADATA
opentelemetry_propagator_gcp-1.11.0.dist-info/WHEEL
opentelemetry_propagator_gcp-1.11.0.dist-info/entry_points.txt
opentelemetry_propagator_gcp-1.11.0.dist-info/top_level.txt
opentelemetry_propagator_gcp-1.11.0.dist-info/RECORD
