Metadata-Version: 2.4
Name: opentelemetry-propagator-gcp
Version: 1.11.0
Summary: Google Cloud propagator for OpenTelemetry
Home-page: https://github.com/GoogleCloudPlatform/opentelemetry-operations-python/tree/main/opentelemetry-propagator-gcp
Author: Google
Author-email: opentelemetry-pypi@google.com
License: Apache-2.0
Platform: any
Classifier: Development Status :: 4 - Beta
Classifier: Intended Audience :: Developers
Classifier: License :: OSI Approved :: Apache Software License
Classifier: Programming Language :: Python
Classifier: Programming Language :: Python :: 3
Classifier: Programming Language :: Python :: 3.9
Classifier: Programming Language :: Python :: 3.10
Classifier: Programming Language :: Python :: 3.11
Classifier: Programming Language :: Python :: 3.12
Classifier: Programming Language :: Python :: 3.13
Requires-Python: >=3.9
License-File: LICENSE
Requires-Dist: opentelemetry-api~=1.0
Provides-Extra: test
Dynamic: license-file
